{
    "version": "https://jsonfeed.org/version/1",
    "title": "Hexo • All posts by \"图片类\" tag",
    "description": "",
    "home_page_url": "http://odiws.github.io",
    "items": [
        {
            "id": "http://odiws.github.io/2024/11/12/FLAG/",
            "url": "http://odiws.github.io/2024/11/12/FLAG/",
            "title": "FLAG",
            "date_published": "2024-11-12T06:58:37.000Z",
            "content_html": "<h3 id=\"flag\"><a class=\"markdownIt-Anchor\" href=\"#flag\">#</a> FLAG</h3>\n<p><img data-src=\"https://zty--666.oss-cn-shanghai.aliyuncs.com/202411121459098.png\" alt=\"image-20241112145948515\"></p>\n<p>直接 stegsolve 打开：</p>\n<p><img data-src=\"https://zty--666.oss-cn-shanghai.aliyuncs.com/202411121500287.png\" alt=\"image-20241112150026054\"></p>\n<p>如图所示提取然后 Save bin，因为首字母为 PK, 设成 zip 文件，这个得放入 L</p>\n<p>inux 系统才能打开，</p>\n<p><img data-src=\"https://zty--666.oss-cn-shanghai.aliyuncs.com/202411121501387.png\" alt=\"image-20241112150151267\"></p>\n<pre><code>file 1   //查看文件类型是elf文件（可拖入ida直接运行）\n</code></pre>\n<p><img data-src=\"https://zty--666.oss-cn-shanghai.aliyuncs.com/202411121502830.png\" alt=\"image-20241112150205585\"></p>\n<p>也可以 strings 1</p>\n<p><img data-src=\"https://zty--666.oss-cn-shanghai.aliyuncs.com/202411121503740.png\" alt=\"image-20241112150334623\"></p>\n<p>获得 flag</p>\n",
            "tags": [
                "图片类"
            ]
        },
        {
            "id": "http://odiws.github.io/2024/11/04/%E6%96%87%E4%BB%B6%E9%87%8C%E7%9A%84%E7%A7%98%E5%AF%86/",
            "url": "http://odiws.github.io/2024/11/04/%E6%96%87%E4%BB%B6%E9%87%8C%E7%9A%84%E7%A7%98%E5%AF%86/",
            "title": "文件里的秘密",
            "date_published": "2024-11-04T13:55:32.000Z",
            "content_html": "<h3 id=\"文件里的秘密\"><a class=\"markdownIt-Anchor\" href=\"#文件里的秘密\">#</a> 文件里的秘密</h3>\n<p>（也是有第二方向哩）</p>\n<p>直接解压后属性里的详细信息</p>\n<p><img data-src=\"https://zty--666.oss-cn-shanghai.aliyuncs.com/202411042157599.png\" alt=\"image-20241104215729394\"></p>\n<p>010editor 也可以直接打开找到</p>\n",
            "tags": [
                "图片类"
            ]
        }
    ]
}